Metadata-Version: 2.1
Name: arcesium-python
Version: 0.0.1
Summary: Arcesium Python Client redirector
Home-page: http://arcesium.com
Author: Arcesium Inc.
Author-email: help@arcesium.com
License: Proprietary
Platform: UNKNOWN
Classifier: Intended Audience :: Financial and Insurance Industry
Classifier: License :: Other/Proprietary License
